qu1ckdr0p2/serv.py
qu1ckdr0p2-2.5.6.dist-info/LICENSE
qu1ckdr0p2-2.5.6.dist-info/METADATA
qu1ckdr0p2-2.5.6.dist-info/WHEEL
qu1ckdr0p2-2.5.6.dist-info/entry_points.txt
qu1ckdr0p2-2.5.6.dist-info/RECORD
